helmsdeep_to_sentry/__init__.py
helmsdeep_to_sentry/format_data.py
helmsdeep_to_sentry/query_helmsdeep.py
test/test_format_data.py
test/test_query_helmsdeep.py
helmsdeep_to_sentry-0.1.0.dist-info/METADATA
helmsdeep_to_sentry-0.1.0.dist-info/WHEEL
helmsdeep_to_sentry-0.1.0.dist-info/top_level.txt
helmsdeep_to_sentry-0.1.0.dist-info/RECORD
