Metadata-Version: 2.2
Name: helmsdeep_to_sentry
Version: 0.1.0
Summary: A package to query helmsdeep for sentry metadata
Author: Lillian Tatka
License: MIT
Classifier: Programming Language :: Python :: 3
Classifier: License :: OSI Approved :: MIT License
Classifier: Operating System :: OS Independent
Requires-Python: >=3.6
Requires-Dist: sqlalchemy
Requires-Dist: pandas
Requires-Dist: python-dotenv
Requires-Dist: mysql-connector-python
